{
    "maps": {
      "darkwood_clearing": {
        "theme": "temperate forest",
        "data": [
          "TTTTTTTTTTT##   ~~~╔╝  .TTTTTTTTTT",
          "TTTTTTTTTTTT#  ~~~ ║  ..TTTTTTTTTT",
          "TTTTTTTTT##   ~~~  ║   ..TTTTTTTTT",
          "TTTTTTT###   ~~~   ║    ....TTTTTT",
          "T╔══════════≡≡≡≡═══╝       ...TTTT",
          "═╝TTTTT###  ~~~  ####    X  TTTTTT",
          "TTTTTT##  ~~~  #TTTTT####..TTTTTTT",
          "TTTTT## ~~~   #TTTTTTTTTTTTTTTTTTT",
          "TTT## ~~~  ###TTTTTTTTTTTTTTTTTTTT",
          "TT#~~~~     #TTTTTTTTTTTTTTTTTTTTT"
        ]
      },
      "darkwood_old_man_tent": {
        "theme": "temperate forest tent",
        "data": [
          "  *                    .          ",
          "         ,                        ",
          "             ╔═══════════════════╗",
          "             ║      [¤]          ║",
          "     Ø &                         ║",
          "             ║h¬              __¶║",
          "     .  *    ╚═══════════════════╝",
          "                     .    *       ",
          "      . ##       ,                ",
          "   ########                       "
        ]
      },
      "darkwood_forest": {
        "theme": "temperate forest",
        "data": [
          "TTTTTTTTTTTTTTTTTTTTTTTTTTTTTTTTTT",
          "═══════════╗TTTTTTTTTTTTTTTTTTTTTT",
          "TTTTTTTTT##║TTTTTTTTTTTTTTTTTTTTTT",
          "TTTTTTT####║TTTTTTTTTTTTTTTTTTTTTT",
          "TTTTTTT### ╚══════════════════════",
          "TTTTTTTTTTTTTTT#TTTTT####..TTTTTTT",
          "TTTTT##TTTTTTT#TTTTTTTTTTTTTTTTTTT",
          "TTT##TTTTTT###TTTTTTTTTTTTTTTTTTTT",
          "TTTTTTTTTTTTTTTTTTTTTTTTTTTTTTTTTT"
        ]
      }
    }
  }
  